{
  "ruleChain": {
    "additionalInfo": null,
    "name": "switchTipoDispositivo",
    "firstRuleNodeId": null,
    "root": false,
    "debugMode": false,
    "configuration": null
  },
  "metadata": {
    "firstNodeIndex": 0,
    "nodes": [
      {
        "additionalInfo": {
          "layoutX": 354,
          "layoutY": 157
        },
        "type": "org.thingsboard.rule.engine.filter.TbJsSwitchNode",
        "name": "al dispositivo",
        "debugMode": true,
        "configuration": {
          "jsScript": "return [metadata.deviceType];"
        }
      }
    ],
    "connections": null,
    "ruleChainConnections": [
      {
        "fromIndex": 0,
        "targetRuleChainId": {
          "entityType": "RULE_CHAIN",
          "id": "40197e90-5433-11eb-a5f7-21c7279bffcd"
        },
        "additionalInfo": {
          "layoutX": 699,
          "layoutY": 263,
          "ruleChainNodeId": "rule-chain-node-12"
        },
        "type": "LGT92"
      },
      {
        "fromIndex": 0,
        "targetRuleChainId": {
          "entityType": "RULE_CHAIN",
          "id": "917844e0-28fc-11eb-800c-43a360f58fa3"
        },
        "additionalInfo": {
          "layoutX": 693,
          "layoutY": 161,
          "ruleChainNodeId": "rule-chain-node-11"
        },
        "type": "LDDS75"
      },
      {
        "fromIndex": 0,
        "targetRuleChainId": {
          "entityType": "RULE_CHAIN",
          "id": "1e18b280-2011-11eb-800c-43a360f58fa3"
        },
        "additionalInfo": {
          "layoutX": 701,
          "layoutY": 438,
          "ruleChainNodeId": "rule-chain-node-10"
        },
        "type": "RAK7204"
      },
      {
        "fromIndex": 0,
        "targetRuleChainId": {
          "entityType": "RULE_CHAIN",
          "id": "f6e720c0-2010-11eb-800c-43a360f58fa3"
        },
        "additionalInfo": {
          "layoutX": 700,
          "layoutY": 322,
          "ruleChainNodeId": "rule-chain-node-9"
        },
        "type": "LHT65"
      },
      {
        "fromIndex": 0,
        "targetRuleChainId": {
          "entityType": "RULE_CHAIN",
          "id": "dd73ee20-2010-11eb-800c-43a360f58fa3"
        },
        "additionalInfo": {
          "layoutX": 695,
          "layoutY": 208,
          "ruleChainNodeId": "rule-chain-node-8"
        },
        "type": "LDS01"
      },
      {
        "fromIndex": 0,
        "targetRuleChainId": {
          "entityType": "RULE_CHAIN",
          "id": "dabec0a0-9de4-11ea-abf5-9397c4646ed8"
        },
        "additionalInfo": {
          "layoutX": 701,
          "layoutY": 384,
          "ruleChainNodeId": "rule-chain-node-7"
        },
        "type": "RAK7200"
      },
      {
        "fromIndex": 0,
        "targetRuleChainId": {
          "entityType": "RULE_CHAIN",
          "id": "313f7fb0-2011-11eb-800c-43a360f58fa3"
        },
        "additionalInfo": {
          "layoutX": 703,
          "layoutY": 497,
          "ruleChainNodeId": "rule-chain-node-6"
        },
        "type": "TTNMAD_CO2_FREE"
      },
      {
        "fromIndex": 0,
        "targetRuleChainId": {
          "entityType": "RULE_CHAIN",
          "id": "496794b0-2011-11eb-800c-43a360f58fa3"
        },
        "additionalInfo": {
          "layoutX": 706,
          "layoutY": 661,
          "ruleChainNodeId": "rule-chain-node-5"
        },
        "type": "TTNMAD_V02_001"
      },
      {
        "fromIndex": 0,
        "targetRuleChainId": {
          "entityType": "RULE_CHAIN",
          "id": "705b1da0-2654-11eb-800c-43a360f58fa3"
        },
        "additionalInfo": {
          "layoutX": 704,
          "layoutY": 554,
          "ruleChainNodeId": "rule-chain-node-4"
        },
        "type": "TTNMAD_DOOR_BME280_TEMT6000"
      },
      {
        "fromIndex": 0,
        "targetRuleChainId": {
          "entityType": "RULE_CHAIN",
          "id": "4fb8d150-53f4-11eb-a5f7-21c7279bffcd"
        },
        "additionalInfo": {
          "layoutX": 704,
          "layoutY": 609,
          "ruleChainNodeId": "rule-chain-node-3"
        },
        "type": "TTNMAD_DOOR"
      }
    ]
  }
}